EPI_MRI/EPIMRIDistortionCorrection.py
EPI_MRI/ImageModels.py
EPI_MRI/InitializationMethods.py
EPI_MRI/LeastSquaresCorrection.py
EPI_MRI/LinearOperators.py
EPI_MRI/Preconditioners.py
EPI_MRI/Regularizers.py
EPI_MRI/__init__.py
EPI_MRI/utils.py
optimization/ADMM.py
optimization/EPIOptimize.py
optimization/GaussNewton.py
optimization/LBFGS.py
optimization/LCurve.py
optimization/LinearSolvers.py
optimization/OptimizationLogger.py
optimization/__init__.py
scripts/__init__.py
scripts/pyhysco.py
simulation/SimulationPipeline.py
PyHySCO-0.0.4.dist-info/LICENSE
PyHySCO-0.0.4.dist-info/METADATA
PyHySCO-0.0.4.dist-info/WHEEL
PyHySCO-0.0.4.dist-info/entry_points.txt
PyHySCO-0.0.4.dist-info/top_level.txt
PyHySCO-0.0.4.dist-info/RECORD
