Metadata-Version: 2.1
Name: PyHySCO
Version: 0.0.4
Summary: Pytorch toolbox for Hyperelastic Susceptibility Artifact Correction
Author-email: Abigail Julian <abigail.julian@emory.edu>, Lars Ruthotto <lars.ruthotto@emory.edu>
Project-URL: Homepage, https://github.com/EmoryMLIP/PyHySCO/
Project-URL: Issues, https://github.com/EmoryMLIP/PyHySCO/issues
Classifier: Programming Language :: Python :: 3
Classifier: License :: OSI Approved :: GNU General Public License v3 (GPLv3)
Classifier: Operating System :: OS Independent
Requires-Python: >=3.8
License-File: LICENSE
Requires-Dist: torch >=2.0.0
Requires-Dist: numpy
Requires-Dist: matplotlib
Requires-Dist: nibabel
Requires-Dist: scipy
